{
	"77":["Москва","Мск", "Москве"],
	"50":["Московская область","Мос", "Московской области"],
	"78":["Санкт-Петербург","Спб", "Санкт-Петербурге"],
	"52":["Нижегородская область","Ниж", "Нижегородской области"],
	"66":["Свердловская область","Свер", "Свердловской области"],
	"86":["Ханты-Мансийский АО","Хан", "Ханты-Мансийском АО"],
	"38":["Иркутская область","Ирк", "Иркутской области"],
	"24":["Красноярский край","Крас", "Красноярском крае"],
	"61":["Ростовская область","Рос", "Ростовской области"],
	"36":["Воронежская область","Вор", "Воронежской области"],
	"74":["Челябинская область","Чел", "Челябинской области"],
	"89":["Ямало-Ненецкий автономный округ","Ямал", "Ямало-Ненецком автономном округе"],
	"51":["Мурманская область","Мур", "Мурманской области"],
	"64":["Саратовская область","Сар", "Саратовской области"],
	"73":["Ульяновская область","Уль", "Ульяновской области"],
	"34":["Волгоградская область","Волг", "Волгоградской области"],
	"22":["Алтайский край","Ал. к.", "Алтайском крае"],
	"26":["Ставропольский край","Став", "Ставропольском крае"],
	"54":["Новосибирская область","Ново", "Новосибирской области"],
	"23":["Краснодарский край","Крдр", "Краснодарском крае"],
	"5":["Республика Дагестан","Даг", "Республике Дагестан"],
	"29":["Архангельская область","Арх", "Архангельской области"],
	"27":["Хабаровский край","Хаб", "Хабаровском крае"],
	"56":["Оренбургская область","Орен", "Оренбургской области"],
	"25":["Приморский край","При", "Приморском крае"],
	"71":["Тульская область","Тул", "Тульской области"],
	"55":["Омская область","Омск", "Омской области"],
	"63":["Самарская область","Сам", "Самарской области"],
	"32":["Брянская область","Бря", "Брянской области"],
	"40":["Калужская область","Калу", "Калужской области"],
	"58":["Пензенская область","Пен", "Пензенской области"],
	"2":["Республика Башкортостан","Бшк", "Республике Башкортостан"],
	"21":["Республика Чувашия","Чув", "Республике Чувашии"],
	"59":["Пермский край","Пер", "Пермском крае"],
	"72":["Тюменская область","Тюм", "Тюменской области"],
	"37":["Ивановская область","Ива", "Ивановской области"],
	"14":["Республика Саха (Якутия)","Саха", "Республике Саха"],
	"31":["Белгородская область","Бел", "Белгородской области"],
	"76":["Ярославская область","Яро", "Ярославской области"],
	"62":["Рязанская область","Ряз", "Рязанской области"],
	"46":["Курская область","Курск", "Курской области"],
	"57":["Орловская область","Орёл", "Орловской области"],
	"17":["Республика Тыва","Тыва", "Республике Тыва"],
	"47":["Ленинградская область","Лен", "Ленинградской области"],
	"68":["Тамбовская область","Там", "Тамбовской области"],
	"11":["Республика Коми","Коми", "Республике Коми"],
	"7":["Кабардино-Балкарская Республика","Каб", "Кабардино-Балкарской Республике"],
	"16":["Республика Татарстан","Тат", "Республике Татарстан"],
	"43":["Кировская область","Кир", "Кировской области"],
	"33":["Владимирская область","Вла", "Владимирской области"],
	"67":["Смоленская область","Смол", "Смоленской области"],
	"42":["Кемеровская область","Кем", "Кемеровской области"],
	"30":["Астраханская область","Аст", "Астраханской области"],
	"70":["Томская область","Том", "Томской области"],
	"13":["Республика Мордовия","Мор", "Республике Мордовии"],
	"69":["Тверская область","Твер", "Тверской области"],
	"3":["Республика Бурятия","Бур", "Республике Бурятии"],
	"48":["Липецкая область","Лип", "Липецкой области"],
	"9":["Карачаево-Черкесская Республика","Кара", "Карачаево-Черкесской Республике"],
	"15":["Республика Северная Осетия — Алания","Осет", "Республике Северная Осетия — Алания"],
	"60":["Псковская область","Пск", "Псковской области"],
	"75":["Забайкальский край","Заб", "Забайкальском крае"],
	"6":["Республика Ингушетия","Инг", "Республике Ингушетии"],
	"53":["Новгородская область","Новг", "Новгородской области"],
	"12":["Республика Марий Эл","Мари", "Республике Марий Эл"],
	"65":["Сахалинская область","Схлн", "Сахалинской области"],
	"8":["Республика Калмыкия","Калм", "Республике Калмыкия"],
	"41":["Камчатский край","Кам", "Камчатском крае"],
	"44":["Костромская область","Кос", "Костромской области"],
	"39":["Калининградская область","Кали", "Калининградской области"],
	"19":["Республика Хакасия","Хак", "Республике Хакасия"],
	"1":["Республика Адыгея","Адыг", "Республике Адыгея"],
	"28":["Амурская область","Амур", "Амурской области"],
	"35":["Вологодская область","Воло", "Вологодской области"],
	"18":["Удмуртская Республика","Удм", "Удмуртской Республике"],
	"10":["Республика Карелия","Кар", "Республике Карелия"],
	"45":["Курганская область","Кург", "Курганской области"],
	"20":["Чеченская Республика","Чеч", "Чеченской Республике"],
	"91":["Республика Крым","Крым", "Республике Крым"],
	"4":["Республика Алтай","Алт", "Республике Алтай"],
	"49":["Магаданская область","Маг", "Магаданской области"],
	"79":["Еврейская автономная область","Евр", "Еврейской автономной области"],
	"92":["Севастополь","Сев", "Севастополе"],
	"83":["Ненецкий автономный округ","Нен", "Ненецком автономном округе"],
	"87":["Чукотский автономный округ","Чук", "Чукотском автономном округе"],
	"100":["Россия","РФ", "России"]
}